dpdata_ani/__init__.py
dpdata_ani/aiqm1.py
dpdata_ani/ani1x.py
dpdata_ani/anidriver.py
dpdata_ani/auto_batch_size.py
dpdata_ani/comp6.py
dpdata_ani/dftd4.py
dpdata_ani/odm2.py
dpdata_ani-0.1.1.dist-info/LICENSE
dpdata_ani-0.1.1.dist-info/METADATA
dpdata_ani-0.1.1.dist-info/WHEEL
dpdata_ani-0.1.1.dist-info/entry_points.txt
dpdata_ani-0.1.1.dist-info/top_level.txt
dpdata_ani-0.1.1.dist-info/RECORD
