Metadata-Version: 2.1
Name: dpdata-ani
Version: 0.1.1
Summary: The dpdata plugin for ANI.
Project-URL: Homepage, https://github.com/njzjz/dpdata_ani
Classifier: Programming Language :: Python
Classifier: Programming Language :: Python :: 3
Requires-Python: >=3.7
License-File: LICENSE
Requires-Dist: dpdata (>=0.2.7)
Requires-Dist: torchani
Requires-Dist: torch
Requires-Dist: numpy
Requires-Dist: h5py
Provides-Extra: aiqm1
Requires-Dist: MLatom ; extra == 'aiqm1'
Requires-Dist: dftd4 ; extra == 'aiqm1'
Provides-Extra: test
Requires-Dist: pytest ; extra == 'test'
Requires-Dist: pytest-cov ; extra == 'test'
